dynamic_valuation/__init__.py
dynamic_valuation/bounded_ivp.py
dynamic_valuation/crunch.py
dynamic_valuation/de.py
dynamic_valuation/fun - Copy.py
dynamic_valuation/fun.py
dynamic_valuation/hc_vfi.py
dynamic_valuation/resource_stocks.py
dynamic_valuation/series_approx.py
dynamic_valuation/time_method.py
dynamic_valuation/vfi.py
jonhamm/__init__.py
jonhamm/bounded_ivp.py
jonhamm/crunch - Copy.py
jonhamm/crunch.py
jonhamm/crunch2.py
jonhamm/crunch3.py
jonhamm/de.py
jonhamm/fun.py
jonhamm/hc_vfi.py
jonhamm/ivp2.py
jonhamm/resource_stocks.py
jonhamm/series_approx.py
jonhamm/time_method.py
jonhamm/vfi.py
jonhamm-0.22.dist-info/METADATA
jonhamm-0.22.dist-info/WHEEL
jonhamm-0.22.dist-info/top_level.txt
jonhamm-0.22.dist-info/RECORD
