Metadata-Version: 2.1
Name: jonhamm
Version: 0.22
Summary: not for you yet
Author: Eric Larson
Author-email: elars213@gmail.com
Requires-Dist: numpy
Requires-Dist: matplotlib
Requires-Dist: scipy
Requires-Dist: pandas
